slack2py/__init__.py
slack2py/webhook.py
slack2py-1.0.0.dist-info/LICENSE
slack2py-1.0.0.dist-info/WHEEL
slack2py-1.0.0.dist-info/METADATA
slack2py-1.0.0.dist-info/RECORD
