Metadata-Version: 2.1
Name: slack2py
Version: 1.0.0
Summary: Simple Slack notification python package,
Home-page: UNKNOWN
License: UNKNOWN
Author: Dhananjay
Author-email: dhananjay@ranium.in
Classifier: License :: OSI Approved :: MIT License
